django_paddle/__init__.py
django_paddle/admin.py
django_paddle/apps.py
django_paddle/client.py
django_paddle/models.py
django_paddle/receivers.py
django_paddle/signals.py
django_paddle/urls.py
django_paddle/utils.py
django_paddle/views.py
django_paddle/management/__init__.py
django_paddle/management/commands/__init__.py
django_paddle/management/commands/paddle_sync_payments.py
django_paddle/management/commands/paddle_sync_plans.py
django_paddle/management/commands/paddle_sync_subscriptions.py
django_paddle/migrations/0001_initial.py
django_paddle/migrations/__init__.py
django_paddle-0.0.8.dist-info/METADATA
django_paddle-0.0.8.dist-info/WHEEL
django_paddle-0.0.8.dist-info/top_level.txt
django_paddle-0.0.8.dist-info/RECORD
